indico_custom_pass/__init__.py
indico_custom_pass/plugin.py
indico_custom_pass/settings.py
indico_custom_pass-1.0.4.dist-info/METADATA
indico_custom_pass-1.0.4.dist-info/WHEEL
indico_custom_pass-1.0.4.dist-info/entry_points.txt
indico_custom_pass-1.0.4.dist-info/licenses/LICENSE
indico_custom_pass-1.0.4.dist-info/RECORD
